simpysql/DBModel.py
simpysql/__init__.py
simpysql/Connections/Connection.py
simpysql/Connections/ConnectionFactory.py
simpysql/Connections/MongoConnection.py
simpysql/Connections/MysqlConnection.py
simpysql/Connections/MysqlConnectionpool.py
simpysql/Connections/PostgresConnection.py
simpysql/Connections/PostgresConnectionpool.py
simpysql/Connections/SqlServerConnection.py
simpysql/Connections/__init__.py
simpysql/Eloquent/BaseBuilder.py
simpysql/Eloquent/BuilderFactory.py
simpysql/Eloquent/MongoBuilder.py
simpysql/Eloquent/MysqlBuilder.py
simpysql/Eloquent/MysqlBuilder_back.py
simpysql/Eloquent/PostgresBuilder.py
simpysql/Eloquent/SqlServerBuilder.py
simpysql/Eloquent/__init__.py
simpysql/Util/Config.py
simpysql/Util/Dynamic.py
simpysql/Util/Expression.py
simpysql/Util/Logger.py
simpysql/Util/MagicMetaClass.py
simpysql/Util/Response.py
simpysql/Util/__init__.py
simpysql-0.4.10.dist-info/LICENSE
simpysql-0.4.10.dist-info/METADATA
simpysql-0.4.10.dist-info/WHEEL
simpysql-0.4.10.dist-info/entry_points.txt
simpysql-0.4.10.dist-info/top_level.txt
simpysql-0.4.10.dist-info/RECORD
