Metadata-Version: 2.1
Name: simpysql
Version: 0.4.10
Summary: A simple mysql orm base on pymysql
Home-page: UNKNOWN
Author: jeanku, liubin
Author-email: 
License: UNKNOWN
Keywords: MySQL ORM
Platform: UNKNOWN
Classifier: Programming Language :: Python :: 3
Classifier: License :: OSI Approved :: MIT License
Classifier: Operating System :: OS Independent
Requires-Python: >=3
Requires-Dist: pymysql
Requires-Dist: pandas
Requires-Dist: configparser
Requires-Dist: DBUtils
Requires-Dist: pymongo
